testfunction/__init__.py
testfunction/__main__.py
sdee-0.0.1.dist-info/LICENSE
sdee-0.0.1.dist-info/METADATA
sdee-0.0.1.dist-info/WHEEL
sdee-0.0.1.dist-info/entry_points.txt
sdee-0.0.1.dist-info/top_level.txt
sdee-0.0.1.dist-info/RECORD
