Metadata-Version: 2.1
Name: sdee
Version: 0.0.1
Summary: A Python Package for Structural Dynamics & Earthquake Engineering
Home-page: https://github.com/mohsen-azimi/sdee
Author: Mohsen Azimi
Author-email: mohsen.azimi@ubc.ca
License: MIT
Platform: UNKNOWN
Classifier: Programming Language :: Python :: 3.8
Classifier: License :: OSI Approved :: MIT License
Classifier: Operating System :: OS Independent
Requires-Python: >=3.8
